grandlite/__init__.py
grandlite-0.1.0.dist-info/LICENSE
grandlite-0.1.0.dist-info/METADATA
grandlite-0.1.0.dist-info/WHEEL
grandlite-0.1.0.dist-info/entry_points.txt
grandlite-0.1.0.dist-info/RECORD
