Metadata-Version: 2.1
Name: grandlite
Version: 0.1.0
Summary: A command-line tool for querying graphs using common query languages.
License: Apache 2.0
Author: Jordan Matelsky
Author-email: opensource@matelsky.com
Requires-Python: >=3.10,<4.0
Classifier: License :: Other/Proprietary License
Classifier: Programming Language :: Python :: 3
Classifier: Programming Language :: Python :: 3.10
Classifier: Programming Language :: Python :: 3.11
Requires-Dist: grand-cypher (>=0.3.0,<0.4.0)
Requires-Dist: grand-graph (>=0.4.2,<0.5.0)
Requires-Dist: prompt-toolkit (>=3.0.38,<4.0.0)
Requires-Dist: requests (>=2.30.0,<3.0.0)
Requires-Dist: tabulate (>=0.9.0,<0.10.0)
